iopatent/__init__.py
iopatent/csv_manager.py
iopatent/exceptions.py
iopatent/json_manager.py
iopatent-0.1.0.dist-info/WHEEL
iopatent-0.1.0.dist-info/METADATA
iopatent-0.1.0.dist-info/RECORD
