Metadata-Version: 2.1
Name: iopatent
Version: 0.1.0
Summary: 
Author: seifnamous
Author-email: senamous@gmail.com
Requires-Python: >=3.8,<4.0
Classifier: Programming Language :: Python :: 3
Classifier: Programming Language :: Python :: 3.10
Classifier: Programming Language :: Python :: 3.8
Classifier: Programming Language :: Python :: 3.9
Requires-Dist: datatest (>=0.11.1,<0.12.0)
Requires-Dist: pandas (>=1.5.0,<2.0.0)
